{"2024-11-22": {"Windows Explorer": 12.45, "Calculator": 34.22, "Task Manager": 7.87, "Microsoft Edge": 21.66, "Visual Studio Code": 45.32}, "2024-11-23": {"Windows Explorer": 18.23, "Calculator": 15.88, "Task Manager": 5.92, "Microsoft Edge": 11.34, "Visual Studio Code": 55.21}, "2024-11-24": {"Windows Explorer": 10.87, "Calculator": 30.12, "Task Manager": 8.45, "Microsoft Edge": 19.56, "Visual Studio Code": 42.76}, "2024-11-25": {"Windows Explorer": 22.11, "Calculator": 28.89, "Task Manager": 9.99, "Microsoft Edge": 14.78, "Visual Studio Code": 39.12}, "2024-11-26": {"Windows Explorer": 17.65, "Calculator": 20.33, "Task Manager": 6.45, "Microsoft Edge": 23.22, "Visual Studio Code": 49.77}, "2024-11-27": {"Windows Explorer": 33.33, "Calculator": 23.05, "Task Manager": 9.01, "Microsoft Edge": 5.0, "Visual Studio Code": 11.38}, "2024-11-28": {"Visual Studio Code": 59.59, "Calculator": 13.07, "Windows Explorer": 1.99}}